{
  "runs": 1,
  "planner": {
    "portfolio_state": "experiments/portfolio_state_degraded_v2.json",
    "ledger": "experiments/action_effectiveness_ledger_synthetic_v2.json",
    "policy": null,
    "top_k": 3,
    "exploration_offset": 0,
    "explain": false
  },
  "output": {
    "experiment_results": "experiments/mapping_regime_high_collision_topk3_results.json",
    "envelope_prefix": "mapping_regime_high_collision_topk3_envelope"
  },
  "mapping_override": {
    "regenerate_missing_artifact": "build_portfolio_dashboard",
    "refresh_repo_health": "build_portfolio_dashboard",
    "rerun_failed_task": "build_portfolio_dashboard",
    "analyze_repo_insights": "repo_insights_example",
    "recover_failed_workflow": "failure_recovery_example"
  }
}
